Metadata-Version: 2.1
Name: Topsis-Aviral-102083032
Version: 0.1
Summary: TYPE YOUR DESCRIPTION HERE
Home-page: https://github.com/aviral1599/avi-topsis
Download-URL: https://github.com/aviral1599/avi-topsis/archive/refs/tags/0.1.tar.gz
Author: Aviral
Author-email: aviralbatra1599@gmail.com
License: MIT
Keywords: SOME,MEANINGFULL,KEYWORDS
Platform: UNKNOWN
Classifier: Development Status :: 3 - Alpha
Classifier: Intended Audience :: Developers
Classifier: Topic :: Software Development :: Build Tools
Classifier: License :: OSI Approved :: MIT License
Classifier: Programming Language :: Python :: 3
Classifier: Programming Language :: Python :: 3.4
Classifier: Programming Language :: Python :: 3.5
Classifier: Programming Language :: Python :: 3.6
Classifier: Programming Language :: Python :: 3.7
Classifier: Programming Language :: Python :: 3.8
Classifier: Programming Language :: Python :: 3.9
License-File: LICENSE
